attribtool/__init__.py
attribtool/__init__.pyi
attribtool/ndattrib.py
attribtool/ndattrib.pyi
attribtool/nnattrib.py
attribtool/nnattrib.pyi
attribtool/py.typed
attribtool-1.0.4.dist-info/LICENSE
attribtool-1.0.4.dist-info/METADATA
attribtool-1.0.4.dist-info/WHEEL
attribtool-1.0.4.dist-info/RECORD
