Metadata-Version: 2.1
Name: attribtool
Version: 1.0.4
Summary: Base classes for restricting the creation of dynamic attributes on instances of derived types.
Home-page: https://github.com/Szumak75/AttribTool
License: MIT
Author: Jacek Kotlarski
Author-email: szumak@virthost.pl
Maintainer: Jacek Kotlarski
Maintainer-email: szumak@virthost.pl
Requires-Python: >=3.7,<4.0
Classifier: License :: OSI Approved :: MIT License
Classifier: Programming Language :: Python :: 3
Classifier: Programming Language :: Python :: 3.7
Classifier: Programming Language :: Python :: 3.8
Classifier: Programming Language :: Python :: 3.9
Classifier: Programming Language :: Python :: 3.10
Classifier: Programming Language :: Python :: 3.11
Classifier: Programming Language :: Python :: 3
Classifier: Topic :: Software Development :: Libraries
Project-URL: Repository, https://github.com/Szumak75/AttribTool
